pygmes/__init__.py
pygmes/api.py
pygmes/diamond.py
pygmes/exec.py
pygmes/printlngs.py
pygmes/prodigal.py
pygmes/version.py
pygmes/data/models/GCA_000409445.2.mod
pygmes/data/models/GCA_001243155.1.mod
pygmes/data/models/GCF_000004695.1.mod
pygmes/data/models/GCF_000151545.1.mod
pygmes/data/models/GCF_000523435.1.mod
pygmes/data/models/GCF_000956335.1.mod
pygmes/data/models/__init__.py
pygmes-0.1.7.dist-info/LICENSE
pygmes-0.1.7.dist-info/METADATA
pygmes-0.1.7.dist-info/WHEEL
pygmes-0.1.7.dist-info/entry_points.txt
pygmes-0.1.7.dist-info/top_level.txt
pygmes-0.1.7.dist-info/RECORD
