Metadata-Version: 2.1
Name: pygmes
Version: 0.1.7
Summary: Run GeneMark-ES using pretrained models
Home-page: https://github.com/openpaul/pygmes
Author: Paul Saary
Author-email: saary@ebi.ac.uk
License: GPLv3
Platform: UNKNOWN
Classifier: Programming Language :: Python :: 3.6
Classifier: License :: OSI Approved :: GNU General Public License v3 (GPLv3)
Classifier: Operating System :: Unix
Requires-Dist: ete3
Requires-Dist: pyfaidx (>=0.5.8)
